sentency/__init__.py
sentency/_version.py
sentency/logs.py
sentency/regex.py
sentency/sentency.py
sentency-0.2.0.dist-info/AUTHORS.rst
sentency-0.2.0.dist-info/LICENSE
sentency-0.2.0.dist-info/METADATA
sentency-0.2.0.dist-info/WHEEL
sentency-0.2.0.dist-info/top_level.txt
sentency-0.2.0.dist-info/RECORD
