Metadata-Version: 2.1
Name: sentency
Version: 0.2.0
Summary: A small lspaCy pipeline component for matching within document sentences using regular expressi
Home-page: https://github.com/g-delong/sentency
Author: Grant DeLong
Author-email: gdelong1@geisinger.edu
License: MIT license
Keywords: sentency
Classifier: Development Status :: 2 - Pre-Alpha
Classifier: Intended Audience :: Developers
Classifier: License :: OSI Approved :: MIT License
Classifier: Natural Language :: English
Classifier: Programming Language :: Python :: 3
Classifier: Programming Language :: Python :: 3.6
Classifier: Programming Language :: Python :: 3.7
Classifier: Programming Language :: Python :: 3.8
Requires-Python: >=3.6
License-File: LICENSE
License-File: AUTHORS.rst
Requires-Dist: spacy
